odoo/addons/stock_picking_batch_creation_split_kit/README.rst
odoo/addons/stock_picking_batch_creation_split_kit/__init__.py
odoo/addons/stock_picking_batch_creation_split_kit/__manifest__.py
odoo/addons/stock_picking_batch_creation_split_kit/i18n/it.po
odoo/addons/stock_picking_batch_creation_split_kit/i18n/stock_picking_batch_creation_split_kit.pot
odoo/addons/stock_picking_batch_creation_split_kit/models/__init__.py
odoo/addons/stock_picking_batch_creation_split_kit/models/stock_device_type.py
odoo/addons/stock_picking_batch_creation_split_kit/readme/CONTRIBUTORS.md
odoo/addons/stock_picking_batch_creation_split_kit/readme/CREDITS.md
odoo/addons/stock_picking_batch_creation_split_kit/readme/DESCRIPTION.md
odoo/addons/stock_picking_batch_creation_split_kit/static/description/icon.png
odoo/addons/stock_picking_batch_creation_split_kit/static/description/index.html
odoo/addons/stock_picking_batch_creation_split_kit/tests/__init__.py
odoo/addons/stock_picking_batch_creation_split_kit/tests/test_make_picking_batch.py
odoo/addons/stock_picking_batch_creation_split_kit/wizards/__init__.py
odoo/addons/stock_picking_batch_creation_split_kit/wizards/make_picking_batch.py
odoo_addon_stock_picking_batch_creation_split_kit-18.0.1.0.0.4.dist-info/METADATA
odoo_addon_stock_picking_batch_creation_split_kit-18.0.1.0.0.4.dist-info/WHEEL
odoo_addon_stock_picking_batch_creation_split_kit-18.0.1.0.0.4.dist-info/top_level.txt
odoo_addon_stock_picking_batch_creation_split_kit-18.0.1.0.0.4.dist-info/RECORD
