Metadata-Version: 2.1
Name: odoo-addon-stock_picking_batch_creation_split_kit
Version: 18.0.1.0.0.4
Requires-Python: >=3.10
Requires-Dist: odoo-addon-stock_picking_batch_creation==18.0.*
Requires-Dist: odoo-addon-stock_split_picking_kit==18.0.*
Requires-Dist: odoo==18.0.*
Summary: Split picking by kit quantity when exceeding limits
Home-page: https://github.com/OCA/stock-logistics-workflow
License: AGPL-3
Author: Camptocamp, BCIM, Odoo Community Association (OCA)
Author-email: support@odoo-community.org
Classifier: Programming Language :: Python
Classifier: Framework :: Odoo
Classifier: Framework :: Odoo :: 18.0
Classifier: License :: OSI Approved :: GNU Affero General Public License v3
